MODApy/__init__.py
MODApy/cfg.py
MODApy/cmd_line.py
MODApy/coverage.py
MODApy/downloader.py
MODApy/modaapi.py
MODApy/parquetvardb.py
MODApy/pipeline.py
MODApy/utils.py
MODApy/variantsdb.py
MODApy/vcfanalysis.py
MODApy/vcfmgr.py
MODApy/version.py
MODApy/www/wespipelinebam.png
MODApy/www/wespipelinefull.png
MODApy/www/wespipelinevcf.png
MODApy-0.8.3.dist-info/LICENSE
MODApy-0.8.3.dist-info/METADATA
MODApy-0.8.3.dist-info/WHEEL
MODApy-0.8.3.dist-info/entry_points.txt
MODApy-0.8.3.dist-info/top_level.txt
MODApy-0.8.3.dist-info/RECORD
