Metadata-Version: 2.1
Name: MODApy
Version: 0.8.3
Summary: Package to perform several analysis on Multi-Omics Data
Home-page: https://github.com/juancgvazquez/MODApy
Author: Juan Carlos Vázquez, Elmer A. Fernández
Author-email: juancgvazquez@gmail.com
Classifier: Programming Language :: Python :: 3
Classifier: License :: OSI Approved :: GNU General Public License (GPL)
Classifier: Development Status :: 3 - Alpha
Classifier: Intended Audience :: Healthcare Industry
Classifier: Intended Audience :: Developers
Classifier: Topic :: Scientific/Engineering :: Bio-Informatics
Classifier: Topic :: Software Development :: Libraries :: Python Modules
License-File: LICENSE
Requires-Dist: pandas (<2.0.0,>=1.3.0)
Requires-Dist: numpy
Requires-Dist: configparser
Requires-Dist: argparse
Requires-Dist: Cython
Requires-Dist: cyvcf2 (==0.9.0)
Requires-Dist: xlrd
Requires-Dist: openpyxl
Requires-Dist: XlsxWriter
Requires-Dist: matplotlib
Requires-Dist: matplotlib-venn
Requires-Dist: xmltodict
Requires-Dist: pyyaml
Requires-Dist: requests
Requires-Dist: tqdm
Requires-Dist: fastapi
Requires-Dist: rq
Requires-Dist: uvicorn
